[{"model": "books.trope", "pk": 1, "fields": {"name": "Enemies to Lovers"}}, {"model": "books.trope", "pk": 2, "fields": {"name": "War academy"}}, {"model": "books.trope", "pk": 3, "fields": {"name": "Grumpy x Sunshine"}}, {"model": "books.trope", "pk": 4, "fields": {"name": "Omegaverse"}}, {"model": "books.trope", "pk": 5, "fields": {"name": "Reverse Harem"}}, {"model": "books.trope", "pk": 6, "fields": {"name": "Shifterverse"}}, {"model": "books.trope", "pk": 7, "fields": {"name": "Urban Fantasy"}}, {"model": "books.trope", "pk": 8, "fields": {"name": "Royals"}}, {"model": "books.trope", "pk": 9, "fields": {"name": "Young Adult"}}, {"model": "books.trope", "pk": 10, "fields": {"name": "Fantasy"}}, {"model": "books.trope", "pk": 11, "fields": {"name": "Bully Romance"}}, {"model": "books.trope", "pk": 13, "fields": {"name": "Slow Burn"}}, {"model": "books.trope", "pk": 14, "fields": {"name": "Mafia"}}, {"model": "books.trope", "pk": 15, "fields": {"name": "Forced Proximity"}}, {"model": "books.trope", "pk": 16, "fields": {"name": "Romantasy"}}, {"model": "books.trope", "pk": 17, "fields": {"name": "Morally Grey"}}, {"model": "books.trope", "pk": 18, "fields": {"name": "Love Triangle"}}, {"model": "books.trope", "pk": 19, "fields": {"name": "Touch her and die"}}, {"model": "books.trope", "pk": 20, "fields": {"name": "Found Family"}}, {"model": "books.trope", "pk": 21, "fields": {"name": "Prof student"}}, {"model": "books.trope", "pk": 22, "fields": {"name": "Fae World"}}, {"model": "books.trope", "pk": 23, "fields": {"name": "Fated Mates"}}, {"model": "books.trope", "pk": 24, "fields": {"name": "Dark Rom"}}, {"model": "books.trope", "pk": 25, "fields": {"name": "Stalker Rom"}}, {"model": "books.trope", "pk": 26, "fields": {"name": "Arrange Marriage"}}, {"model": "books.trope", "pk": 27, "fields": {"name": "Brother's Best Friend"}}, {"model": "books.trope", "pk": 28, "fields": {"name": "Contemporary"}}, {"model": "books.trope", "pk": 29, "fields": {"name": "Age Gap"}}, {"model": "books.trope", "pk": 30, "fields": {"name": "Captive Romance"}}, {"model": "books.trope", "pk": 31, "fields": {"name": "Werewolf"}}, {"model": "books.trope", "pk": 32, "fields": {"name": "Virgin fmc"}}, {"model": "books.trope", "pk": 33, "fields": {"name": "Forbidden Love"}}, {"model": "books.trope", "pk": 34, "fields": {"name": "Trauma"}}, {"model": "books.trope", "pk": 35, "fields": {"name": "Marriage in Trouble"}}, {"model": "books.trope", "pk": 36, "fields": {"name": "Epilogues"}}, {"model": "books.trope", "pk": 37, "fields": {"name": "Fake Dating"}}, {"model": "books.trope", "pk": 38, "fields": {"name": "Pregnancy"}}, {"model": "books.trope", "pk": 39, "fields": {"name": "Single Dad"}}, {"model": "books.trope", "pk": 40, "fields": {"name": "Second Chance"}}]
